pyclier/__init__.py
pyclier/argparse.py
pyclier/command.py
pyclier/common.py
pyclier/config.py
pyclier/setuptools.py
pyclier/utils.py
pyclier/actors/__init__.py
pyclier/actors/actions.py
pyclier/actors/actor.py
pyclier/actors/displayer.py
pyclier/actors/filter.py
pyclier/actors/persister.py
pyclier/actors/sorter.py
pyclier-2.0.0.dist-info/LICENSE
pyclier-2.0.0.dist-info/METADATA
pyclier-2.0.0.dist-info/WHEEL
pyclier-2.0.0.dist-info/top_level.txt
pyclier-2.0.0.dist-info/RECORD
