Metadata-Version: 2.1
Name: pyclier
Version: 2.0.0
Summary: A python CLI framework base on argparse, supporting: config system, command-completion, rich-text log and so on.
Home-page: https://github.com/zhangxianbing/pyclier
Author: zhangxianbing
License: Apache License 2.0
Keywords: options,argparse,config,cli,YAML,INI
Platform: UNKNOWN
Classifier: Development Status :: 3 - Alpha
Classifier: Intended Audience :: Developers
Classifier: License :: OSI Approved :: Apache Software License
Classifier: Programming Language :: Python :: 3.6
Classifier: Programming Language :: Python :: 3.7
Classifier: Programming Language :: Python :: 3.8
Classifier: Programming Language :: Python :: 3.9
Classifier: Programming Language :: Python :: Implementation :: CPython
Requires-Python: >=3.6
License-File: LICENSE
Requires-Dist: appdirs (>=1.4.4)
Requires-Dist: PyYAML (>=5.4.1)
Requires-Dist: setuptools (>=40.6.2)
Requires-Dist: rich (>=10.1.0)
Requires-Dist: pyclier (>=0.1.1)
Requires-Dist: argcomplete (>=1.12.3)
